{
    "os": "Linux-6.5.0-28-generic-x86_64-with-glibc2.35",
    "python": "3.12.3",
    "heartbeatAt": "2024-05-12T14:15:39.789308",
    "startedAt": "2024-05-12T14:15:39.034850",
    "docker": null,
    "cuda": null,
    "args": [],
    "state": "running",
    "program": "/mnt/data/kai/VinDr_YOLOv8/traintest.py",
    "codePathLocal": "traintest.py",
    "codePath": "traintest.py",
    "host": "thermaltake",
    "username": "kai",
    "executable": "/home/kai/miniconda3/envs/vindr/bin/python3",
    "cpu_count": 10,
    "cpu_count_logical": 20,
    "cpu_freq": {
        "current": 1993.5387999999996,
        "min": 1200.0,
        "max": 4120.0
    },
    "cpu_freq_per_core": [
        {
            "current": 3503.564,
            "min": 1200.0,
            "max": 4100.0
        },
        {
            "current": 1200.0,
            "min": 1200.0,
            "max": 4100.0
        },
        {
            "current": 3396.741,
            "min": 1200.0,
            "max": 4100.0
        },
        {
            "current": 4000.0,
            "min": 1200.0,
            "max": 4200.0
        },
        {
            "current": 3991.069,
            "min": 1200.0,
            "max": 4100.0
        },
        {
            "current": 1200.0,
            "min": 1200.0,
            "max": 4100.0
        },
        {
            "current": 3389.095,
            "min": 1200.0,
            "max": 4100.0
        },
        {
            "current": 1899.846,
            "min": 1200.0,
            "max": 4100.0
        },
        {
            "current": 1200.0,
            "min": 1200.0,
            "max": 4100.0
        },
        {
            "current": 3685.401,
            "min": 1200.0,
            "max": 4200.0
        },
        {
            "current": 1200.0,
            "min": 1200.0,
            "max": 4100.0
        },
        {
            "current": 2000.512,
            "min": 1200.0,
            "max": 4100.0
        },
        {
            "current": 1200.0,
            "min": 1200.0,
            "max": 4100.0
        },
        {
            "current": 4003.228,
            "min": 1200.0,
            "max": 4200.0
        },
        {
            "current": 3000.896,
            "min": 1200.0,
            "max": 4100.0
        },
        {
            "current": 1200.0,
            "min": 1200.0,
            "max": 4100.0
        },
        {
            "current": 1200.0,
            "min": 1200.0,
            "max": 4100.0
        },
        {
            "current": 1200.0,
            "min": 1200.0,
            "max": 4100.0
        },
        {
            "current": 1200.0,
            "min": 1200.0,
            "max": 4100.0
        },
        {
            "current": 1765.096,
            "min": 1200.0,
            "max": 4200.0
        }
    ],
    "disk": {
        "/": {
            "total": 3753.976058959961,
            "used": 239.18634033203125
        }
    },
    "gpu": "NVIDIA GeForce RTX 2080 Ti",
    "gpu_count": 2,
    "gpu_devices": [
        {
            "name": "NVIDIA GeForce RTX 2080 Ti",
            "memory_total": 11811160064
        },
        {
            "name": "NVIDIA GeForce RTX 2080 Ti",
            "memory_total": 11811160064
        }
    ],
    "memory": {
        "total": 62.469051361083984
    }
}
